[{"city_type": "Hansestadt", "category_variance_rank_std": 75.75757575757575, "open_formats": 648.0, "dataset_rank": 21.0, "overall_rank_data": 15.756402842614863, "id": "rostock", "days_between_start_and_last_update": null, "dataset_score_rank_std": 3.225806451612903, "formats_rank_std": 7.228915662650603, "formats_rank": 6.0, "dataset_rank_std": 20.58823529411765, "days_since_last_update": 0.0, "last_update_rank_std": 1.2048192771084338, "format_count": 8.0, "latitude": 54.0924445, "category_score": 1.0, "category_rank_std": 1.0101010101010102, "dataset_score_rank": 2.0, "days_since_start": null, "open_license_and_format_count": false, "category_count": 14.0, "contact_email": null, "dataset_score": 2.1614583333333335, "open_formats_datasets": false, "datasets": 192.0, "name": "Rostock", "last_update_rank": 1.0, "overall_rank": 1.0, "created_at": "2015-01-05T17:19:25.567128", "category_score_rank": 1.0, "longitude": 12.1286127, "category_rank": 1.0, "category_variance_rank": 75.0, "category_score_rank_std": 2.857142857142857, "portal": "http://opendata-hro.de ", "contact_person": "OB Ulrich Kunze", "category_variance": 233.63186813186815, "open_datasets": 192.0}, {"city_type": "Landeshauptstadt", "category_variance_rank_std": 71.71717171717172, "open_formats": 112.0, "dataset_rank": 25.0, "overall_rank_data": 17.888297318008572, "id": "muenchen", "days_between_start_and_last_update": null, "dataset_score_rank_std": 1.6129032258064515, "formats_rank_std": 13.25301204819277, "formats_rank": 11.0, "dataset_rank_std": 24.50980392156863, "days_since_last_update": 0.0, "last_update_rank_std": 1.2048192771084338, "format_count": 6.0, "latitude": 48.1372719, "category_score": 0.5, "category_rank_std": 9.090909090909092, "dataset_score_rank": 1.0, "days_since_start": null, "open_license_and_format_count": false, "category_count": 12.0, "contact_email": null, "dataset_score": 2.163551401869159, "open_formats_datasets": false, "datasets": 107.0, "name": "M\u00fcnchen", "last_update_rank": 1.0, "overall_rank": 2.0, "created_at": "2015-01-05T17:19:10.861727", "category_score_rank": 5.0, "longitude": 11.5754815, "category_rank": 9.0, "category_variance_rank": 71.0, "category_score_rank_std": 14.285714285714286, "portal": "http://www.opengov-muenchen.de", "contact_person": "Dr. Daniela Rothenh\u00f6fer", "category_variance": 132.5681818181818, "open_datasets": 107.0}, {"city_type": "Stadt", "category_variance_rank_std": 43.43434343434343, "open_formats": 295.0, "dataset_rank": 28.0, "overall_rank_data": 22.430080112460487, "id": "frankfurt", "days_between_start_and_last_update": null, "dataset_score_rank_std": 24.193548387096776, "formats_rank_std": 2.4096385542168677, "formats_rank": 2.0, "dataset_rank_std": 27.45098039215686, "days_since_last_update": 0.0, "last_update_rank_std": 1.2048192771084338, "format_count": 10.0, "latitude": 50.12134215, "category_score": 0.5, "category_rank_std": 9.090909090909092, "dataset_score_rank": 15.0, "days_since_start": null, "open_license_and_format_count": false, "category_count": 12.0, "contact_email": null, "dataset_score": 1.8181818181818181, "open_formats_datasets": false, "datasets": 77.0, "name": "Frankfurt am Main", "last_update_rank": 1.0, "overall_rank": 3.0, "created_at": "2015-01-05T17:19:28.266295", "category_score_rank": 5.0, "longitude": 8.661951186, "category_rank": 9.0, "category_variance_rank": 43.0, "category_score_rank_std": 14.285714285714286, "portal": "http://offenedaten.frankfurt.de", "contact_person": "OB Peter Feldmann", "category_variance": 14.386363636363637, "open_datasets": 77.0}, {"city_type": "Stadt", "category_variance_rank_std": 45.45454545454545, "open_formats": 117.0, "dataset_rank": 38.0, "overall_rank_data": 26.55426935404531, "id": "meerbusch", "days_between_start_and_last_update": null, "dataset_score_rank_std": 27.419354838709676, "formats_rank_std": 19.27710843373494, "formats_rank": 16.0, "dataset_rank_std": 37.254901960784316, "days_since_last_update": 0.0, "last_update_rank_std": 1.2048192771084338, "format_count": 4.0, "latitude": 51.2851, "category_score": 0.5, "category_rank_std": 23.232323232323232, "dataset_score_rank": 17.0, "days_since_start": null, "open_license_and_format_count": false, "category_count": 8.0, "contact_email": null, "dataset_score": 1.7738095238095237, "open_formats_datasets": false, "datasets": 42.0, "name": "Meerbusch", "last_update_rank": 1.0, "overall_rank": 4.0, "created_at": "2017-11-27T13:09:44.401376", "category_score_rank": 5.0, "longitude": 6.62494, "category_rank": 23.0, "category_variance_rank": 45.0, "category_score_rank_std": 14.285714285714286, "portal": null, "contact_person": null, "category_variance": 16.125, "open_datasets": 42.0}, {"city_type": "Stadt", "category_variance_rank_std": 80.8080808080808, "open_formats": 344.0, "dataset_rank": 12.0, "overall_rank_data": 28.77600431874454, "id": "moers", "days_between_start_and_last_update": null, "dataset_score_rank_std": 29.032258064516128, "formats_rank_std": 4.819277108433735, "formats_rank": 4.0, "dataset_rank_std": 11.764705882352942, "days_since_last_update": 0.0, "last_update_rank_std": 1.2048192771084338, "format_count": 9.0, "latitude": 51.4512826, "category_score": 0.5, "category_rank_std": 14.141414141414142, "dataset_score_rank": 18.0, "days_since_start": null, "open_license_and_format_count": false, "category_count": 11.0, "contact_email": null, "dataset_score": 1.6390728476821192, "open_formats_datasets": false, "datasets": 302.0, "name": "Moers", "last_update_rank": 1.0, "overall_rank": 5.0, "created_at": "2015-01-05T17:19:24.709466", "category_score_rank": 5.0, "longitude": 6.6284302, "category_rank": 14.0, "category_variance_rank": 80.0, "category_score_rank_std": 14.285714285714286, "portal": "http://offenedaten.moers.de", "contact_person": "Claus Arndt", "category_variance": 470.2909090909091, "open_datasets": 299.0}]